evmath/__init__.py
evmath/geo.py
evmath-1.1.1.dist-info/LICENSE.txt
evmath-1.1.1.dist-info/METADATA
evmath-1.1.1.dist-info/WHEEL
evmath-1.1.1.dist-info/top_level.txt
evmath-1.1.1.dist-info/RECORD
