Metadata-Version: 2.1
Name: evmath
Version: 1.1.1
Summary: Evmath math module
Home-page: https://github.com/ballandt/evmath
Author: Camillo Ballandt
Author-email: ballandt@protonmail.com
License: UNKNOWN
Project-URL: Documentation, https://ballandt.github.io/docs/evmath.html
Platform: UNKNOWN
Classifier: Programming Language :: Python :: 3
Classifier: License :: OSI Approved :: MIT License
Classifier: Operating System :: OS Independent
Requires-Python: >=3.6
License-File: LICENSE.txt
